Authenticator.py
BioRanker.py
Generator.py
Synthesizer.py
Gcoupler-2.1.8.dist-info/LICENSE.txt
Gcoupler-2.1.8.dist-info/METADATA
Gcoupler-2.1.8.dist-info/WHEEL
Gcoupler-2.1.8.dist-info/top_level.txt
Gcoupler-2.1.8.dist-info/RECORD
