Metadata-Version: 2.1
Name: Gcoupler
Version: 2.1.8
Summary: Interactome Prediction using Gcoupler
Home-page: https://github.com/the-ahuja-lab/Gcoupler
Author: Sanjay Kumar Mohanty
Author-email: sanjaym@iiitd.ac.in
Classifier: Programming Language :: Python :: 3.8
Classifier: License :: OSI Approved :: MIT License
Classifier: Operating System :: Unix
License-File: LICENSE.txt
Provides-Extra: dev
Requires-Dist: seaborn (>=0.11.2) ; extra == 'dev'
Requires-Dist: pandas (>=1.3.5) ; extra == 'dev'
Requires-Dist: numpy (>=1.21.6) ; extra == 'dev'
Requires-Dist: py3Dmol (>=0.9.2) ; extra == 'dev'
Requires-Dist: scipy (>=1.5.2) ; extra == 'dev'
Requires-Dist: matplotlib (>=3.2.2) ; extra == 'dev'
Requires-Dist: rdkit-pypi (>=2020.9.5) ; extra == 'dev'
Requires-Dist: deepchem (==2.7.2.dev20230810062656) ; extra == 'dev'
Requires-Dist: imblearn ; extra == 'dev'
Requires-Dist: vina (>=1.2.0.dev3) ; extra == 'dev'
Requires-Dist: scikit-learn (>=0.22.2) ; extra == 'dev'
Requires-Dist: dgl (>=0.7.2) ; extra == 'dev'
